thz_deconvolution/__init__.py
thz_deconvolution/utils.py
thz_deconvolution-1.0.3.dist-info/licenses/LICENSE
thz_deconvolution-1.0.3.dist-info/METADATA
thz_deconvolution-1.0.3.dist-info/WHEEL
thz_deconvolution-1.0.3.dist-info/top_level.txt
thz_deconvolution-1.0.3.dist-info/RECORD
