Metadata-Version: 2.4
Name: thz_deconvolution
Version: 1.0.3
Summary: This Python Package is designed for advanced signal processing in THz time-domain spectroscopy.
Author-email: Arnaud Demion <arnaud.demion@hevs.ch>
Project-URL: Homepage, https://github.com/Arnwald/thz_deconvolution
Project-URL: Bug Tracker, https://github.com/Arnwald/thz_deconvolution/issues
Classifier: Programming Language :: Python :: 3
Classifier: License :: OSI Approved :: MIT License
Classifier: Operating System :: OS Independent
Requires-Python: >=3.7
License-File: LICENSE
Requires-Dist: numpy
Requires-Dist: scipy
Requires-Dist: matplotlib
Requires-Dist: zmq
Requires-Dist: tqdm
Requires-Dist: pydotthz
Dynamic: license-file
